{"publications":[
{"date":"2011-10-04T00:00:00.000Z","urlDoc":"https://zoek.officielebekendmakingen.nl/stcrt-2011-17440.html","urlApi":"https://repository.overheid.nl/frbr/officielepublicaties/stcrt/2011/stcrt-2011-17440/1/xml/stcrt-2011-17440.xml","type":"ruimtelijke plannen","title":"Ontwerpbestemmingsplan ‘Terherne-Kom Waterpark De Zoutpoel’","description":"Ontwerpbestemmingsplan ‘Terherne-Kom Waterpark De Zoutpoel’","location":[]},
{"date":"2011-10-18T00:00:00.000Z","urlDoc":"https://zoek.officielebekendmakingen.nl/stcrt-2011-18444.html","urlApi":"https://repository.overheid.nl/frbr/officielepublicaties/stcrt/2011/stcrt-2011-18444/1/xml/stcrt-2011-18444.xml","type":"ruimtelijke plannen","title":"Gewijzigde vaststelling bestemmingsplan ‘Tusken de Marren bestaande camping’","description":"Gewijzigde vaststelling bestemmingsplan ‘Tusken de Marren bestaande camping’","location":[]},
{"date":"2011-10-18T00:00:00.000Z","urlDoc":"https://zoek.officielebekendmakingen.nl/stcrt-2011-18652.html","urlApi":"https://repository.overheid.nl/frbr/officielepublicaties/stcrt/2011/stcrt-2011-18652/1/xml/stcrt-2011-18652.xml","type":"ruimtelijke plannen","title":"Vaststelling bestemmingsplan en Beeldkwaliteitsplan Molehiem te Jirnsum","description":"Vaststelling bestemmingsplan en Beeldkwaliteitsplan Molehiem te Jirnsum","location":[]}
]}