{"publications":[
{"date":"2021-05-09T15:47:19.150Z","urlDoc":"https://zoek.officielebekendmakingen.nl/gmb-2018-68115.html","urlApi":"https://repository.overheid.nl/frbr/officielepublicaties/gmb/2018/gmb-2018-68115/1/xml/gmb-2018-68115.xml","type":"Beschikkingen | aanvraag","title":"Aanvragen vergunningen APV/evenementen/horeca","description":"Aanvragen vergunningen APV/evenementen/horeca","location":["52.6928272678944 6.21864436983401","52.6910945624522 6.20279976669534"]},
{"date":"2021-05-09T15:47:19.455Z","urlDoc":"https://zoek.officielebekendmakingen.nl/gmb-2018-68116.html","urlApi":"https://repository.overheid.nl/frbr/officielepublicaties/gmb/2018/gmb-2018-68116/1/xml/gmb-2018-68116.xml","type":"Beschikkingen | aanvraag","title":"Verleende vergunningen APV/evenementen/horeca","description":"Verleende vergunningen APV/evenementen/horeca","location":["52.6988698295981 6.19338740285033","52.7008869469976 6.23924304853773","52.6848354304928 6.17267653736744","52.6970440626792 6.19225918428036"]},
{"date":"2021-05-09T15:47:20.069Z","urlDoc":"https://zoek.officielebekendmakingen.nl/gmb-2018-68118.html","urlApi":"https://repository.overheid.nl/frbr/officielepublicaties/gmb/2018/gmb-2018-68118/1/xml/gmb-2018-68118.xml","type":"Beschikkingen | aanvraag","title":"Verleende omgevingsvergunningen reguliere procedure","description":"Verleende omgevingsvergunningen reguliere procedure","location":["52.6888805925993 6.17118110239019"]},
{"date":"2021-05-09T15:47:21.169Z","urlDoc":"https://zoek.officielebekendmakingen.nl/gmb-2018-68122.html","urlApi":"https://repository.overheid.nl/frbr/officielepublicaties/gmb/2018/gmb-2018-68122/1/xml/gmb-2018-68122.xml","type":"Beschikkingen | aanvraag","title":"Aanvragen omgevingsvergunningen","description":"Aanvragen omgevingsvergunningen","location":["52.6907876711954 6.26485769070795"]},
{"date":"2021-05-09T16:33:28.316Z","urlDoc":"https://zoek.officielebekendmakingen.nl/gmb-2018-75707.html","urlApi":"https://repository.overheid.nl/frbr/officielepublicaties/gmb/2018/gmb-2018-75707/1/xml/gmb-2018-75707.xml","type":"Beschikkingen | afhandeling","title":"Verleende vergunningen APV/evenementen/horeca WEEK 15","description":"Verleende vergunningen APV/evenementen/horeca WEEK 15","location":["52.6971378269523 6.1916839683139","52.7324605744714 6.16831789178847","52.69744955401 6.18944109644852","52.6970987936658 6.18947906718606","52.7354555276722 6.15554916520745","52.6971440116168 6.19209829155642","52.6890623780191 6.17766256989343"]},
{"date":"2021-05-09T16:33:29.046Z","urlDoc":"https://zoek.officielebekendmakingen.nl/gmb-2018-75709.html","urlApi":"https://repository.overheid.nl/frbr/officielepublicaties/gmb/2018/gmb-2018-75709/1/xml/gmb-2018-75709.xml","type":"Beschikkingen | aanvraag","title":"Aanvragen vergunningen APV/evenementen/horeca WEEK 15","description":"Aanvragen vergunningen APV/evenementen/horeca WEEK 15","location":["52.7325175990379 6.16784514411189","52.7354555276722 6.15554916520745","52.6972508604313 6.18958539848622","52.6919029433008 6.17892659707658","52.6970882111818 6.18971556484787","52.69744955401 6.18944109644852"]},
{"date":"2021-05-09T16:33:29.173Z","urlDoc":"https://zoek.officielebekendmakingen.nl/gmb-2018-75710.html","urlApi":"https://repository.overheid.nl/frbr/officielepublicaties/gmb/2018/gmb-2018-75710/1/xml/gmb-2018-75710.xml","type":"Beschikkingen | afhandeling","title":"Verleende omgevingsvergunningen reguliere procedure WEEK 15.","description":"Verleende omgevingsvergunningen reguliere procedure WEEK 15.","location":["52.6912980574409 6.16983388579463","52.6923947021381 6.19269165324618","52.7115868195752 6.14554214809748","52.6907382787897 6.25073114191508","52.6959841147522 6.22981359443631"]},
{"date":"2021-05-09T16:33:29.781Z","urlDoc":"https://zoek.officielebekendmakingen.nl/gmb-2018-75711.html","urlApi":"https://repository.overheid.nl/frbr/officielepublicaties/gmb/2018/gmb-2018-75711/1/xml/gmb-2018-75711.xml","type":"Beschikkingen | afhandeling","title":"Kennisgeving verlenging beslistermijn","description":"Kennisgeving verlenging beslistermijn","location":["52.7009494426327 6.18753738342412","52.6910672830174 6.17348318287086"]},
{"date":"2021-05-09T16:33:29.909Z","urlDoc":"https://zoek.officielebekendmakingen.nl/gmb-2018-75712.html","urlApi":"https://repository.overheid.nl/frbr/officielepublicaties/gmb/2018/gmb-2018-75712/1/xml/gmb-2018-75712.xml","type":"Beschikkingen | aanvraag","title":"Aanvragen omgevingsvergunningen WEEK 15","description":"Aanvragen omgevingsvergunningen WEEK 15","location":["52.7058830295865 6.17684094777584","52.697977305112 6.19776468358727","52.679543830133 6.17916225189641","52.7001129151308 6.23310319288689","52.7016604781845 6.19005065491177","52.6782487282217 6.17930156003774","52.6827514969797 6.18733888878056"]},
{"date":"2021-05-09T16:58:28.781Z","urlDoc":"https://zoek.officielebekendmakingen.nl/gmb-2018-79547.html","urlApi":"https://repository.overheid.nl/frbr/officielepublicaties/gmb/2018/gmb-2018-79547/1/xml/gmb-2018-79547.xml","type":"Overige besluiten van algemene strekking","title":"Besluit ambtshalve wijziging adresgegevens naar onbekende bestemming, gemeente Meppel","description":"Besluit ambtshalve wijziging adresgegevens naar onbekende bestemming, gemeente Meppel","location":[]},
{"date":"2021-05-09T17:05:30.954Z","urlDoc":"https://zoek.officielebekendmakingen.nl/gmb-2018-80515.html","urlApi":"https://repository.overheid.nl/frbr/officielepublicaties/gmb/2018/gmb-2018-80515/1/xml/gmb-2018-80515.xml","type":"Overige overheidsinformatie","title":"Melding Activiteitenbesluit milieubeheer","description":"Melding Activiteitenbesluit milieubeheer","location":["52.7138347850852 6.19586732616698"]},
{"date":"2021-05-09T17:05:33.715Z","urlDoc":"https://zoek.officielebekendmakingen.nl/gmb-2018-80521.html","urlApi":"https://repository.overheid.nl/frbr/officielepublicaties/gmb/2018/gmb-2018-80521/1/xml/gmb-2018-80521.xml","type":"Beschikkingen | afhandeling","title":"Verleende vergunningen APV/evenementen/horeca WEEK 16","description":"Verleende vergunningen APV/evenementen/horeca WEEK 16","location":["52.6956637757726 6.18770730784573","52.6972508604313 6.18958539848622","52.6985647280567 6.19199119359377","52.6967799800131 6.1914407223621","52.697588836068 6.19144074482474","52.6909877748337 6.192088992919","52.6964799439466 6.18929024386647"]},
{"date":"2021-05-09T17:05:35.443Z","urlDoc":"https://zoek.officielebekendmakingen.nl/gmb-2018-80525.html","urlApi":"https://repository.overheid.nl/frbr/officielepublicaties/gmb/2018/gmb-2018-80525/1/xml/gmb-2018-80525.xml","type":"Beschikkingen | aanvraag","title":"Aanvragen vergunningen APV/evenementen/horeca WEEK 16","description":"Aanvragen vergunningen APV/evenementen/horeca WEEK 16","location":["52.6972508604313 6.18958539848622","52.6964799439466 6.18929024386647","52.7321321021077 6.16632817616424","52.6887373528073 6.26623660570033","52.697034143615 6.22237795685402"]},
{"date":"2021-05-09T17:05:36.743Z","urlDoc":"https://zoek.officielebekendmakingen.nl/gmb-2018-80528.html","urlApi":"https://repository.overheid.nl/frbr/officielepublicaties/gmb/2018/gmb-2018-80528/1/xml/gmb-2018-80528.xml","type":"Beschikkingen | afhandeling","title":"Verleende omgevingsvergunningen reguliere procedure WEEK 16","description":"Verleende omgevingsvergunningen reguliere procedure WEEK 16","location":["52.6831590592034 6.1868730810179"]},
{"date":"2021-05-09T17:05:38.435Z","urlDoc":"https://zoek.officielebekendmakingen.nl/gmb-2018-80531.html","urlApi":"https://repository.overheid.nl/frbr/officielepublicaties/gmb/2018/gmb-2018-80531/1/xml/gmb-2018-80531.xml","type":"Beschikkingen | aanvraag","title":"Kennisgeving verlenging beslistermijn","description":"Kennisgeving verlenging beslistermijn","location":["52.6834276941638 6.19101877628979"]},
{"date":"2021-05-09T17:05:40.195Z","urlDoc":"https://zoek.officielebekendmakingen.nl/gmb-2018-80535.html","urlApi":"https://repository.overheid.nl/frbr/officielepublicaties/gmb/2018/gmb-2018-80535/1/xml/gmb-2018-80535.xml","type":"Beschikkingen | aanvraag","title":"Aanvragen omgevingsvergunningen WEEK 16","description":"Aanvragen omgevingsvergunningen WEEK 16","location":["52.6984514090102 6.1914713386354","52.6839949228075 6.17338615588501","52.6824974565772 6.18233582656921"]},
{"date":"2021-05-09T17:23:52.397Z","urlDoc":"https://zoek.officielebekendmakingen.nl/gmb-2018-83368.html","urlApi":"https://repository.overheid.nl/frbr/officielepublicaties/gmb/2018/gmb-2018-83368/1/xml/gmb-2018-83368.xml","type":"Plannen | ruimtelijk","title":"Ontwerp bestemmingsplan ‘Meppel –Haveltermade 2017’","description":"Ontwerp bestemmingsplan ‘Meppel –Haveltermade 2017’","location":["52.7045185666882 6.19534060342163"]},
{"date":"2021-05-09T17:37:22.571Z","urlDoc":"https://zoek.officielebekendmakingen.nl/gmb-2018-85608.html","urlApi":"https://repository.overheid.nl/frbr/officielepublicaties/gmb/2018/gmb-2018-85608/1/xml/gmb-2018-85608.xml","type":"Overige besluiten van algemene strekking","title":"Besluit ambtshalve wijziging adresgegevens naar onbekende bestemming, gemeente Meppel","description":"Besluit ambtshalve wijziging adresgegevens naar onbekende bestemming, gemeente Meppel","location":[]},
{"date":"2021-05-09T17:48:00.187Z","urlDoc":"https://zoek.officielebekendmakingen.nl/gmb-2018-87355.html","urlApi":"https://repository.overheid.nl/frbr/officielepublicaties/gmb/2018/gmb-2018-87355/1/xml/gmb-2018-87355.xml","type":"Beschikkingen | afhandeling","title":"Verleende vergunningen APV/evenementen/horeca WEEK 17","description":"Verleende vergunningen APV/evenementen/horeca WEEK 17","location":["52.6964799439466 6.18929024386647","52.6971978411731 6.18945129054706","52.7045100082808 6.17653513164581","52.6968890950337 6.19258179168259","52.6928272678944 6.21864436983401","52.697588836068 6.19144074482474"]},
{"date":"2021-05-09T17:48:01.733Z","urlDoc":"https://zoek.officielebekendmakingen.nl/gmb-2018-87358.html","urlApi":"https://repository.overheid.nl/frbr/officielepublicaties/gmb/2018/gmb-2018-87358/1/xml/gmb-2018-87358.xml","type":"Beschikkingen | aanvraag","title":"Aanvragen vergunningen APV/evenementen/horeca WEEK 17","description":"Aanvragen vergunningen APV/evenementen/horeca WEEK 17","location":["52.6996579053298 6.19380131352304","52.6956637757726 6.18770730784573","52.7060801867774 6.20093273697025","52.7321321021077 6.16632817616424","52.7033981553733 6.19357412953367"]},
{"date":"2021-05-09T17:48:02.449Z","urlDoc":"https://zoek.officielebekendmakingen.nl/gmb-2018-87359.html","urlApi":"https://repository.overheid.nl/frbr/officielepublicaties/gmb/2018/gmb-2018-87359/1/xml/gmb-2018-87359.xml","type":"Beschikkingen | aanvraag","title":"Kennisgeving verlenging beslistermijn","description":"Kennisgeving verlenging beslistermijn","location":["52.6937282394481 6.21574738498996","52.6937484701761 6.19450632645541"]},
{"date":"2021-05-09T17:48:03.199Z","urlDoc":"https://zoek.officielebekendmakingen.nl/gmb-2018-87362.html","urlApi":"https://repository.overheid.nl/frbr/officielepublicaties/gmb/2018/gmb-2018-87362/1/xml/gmb-2018-87362.xml","type":"Beschikkingen | aanvraag","title":"Aanvragen omgevingsvergunningen WEEK 17","description":"Aanvragen omgevingsvergunningen WEEK 17","location":["52.7043834163879 6.17665122037565","52.698869253264 6.21699831993602","52.6797999108841 6.18119273587444","52.731112471012 6.17649565120743","52.7078511725432 6.17955457494288","52.7072457333917 6.17599246350233","52.7236720822518 6.15574244632693"]},
{"date":"2021-05-09T17:48:10.309Z","urlDoc":"https://zoek.officielebekendmakingen.nl/gmb-2018-87384.html","urlApi":"https://repository.overheid.nl/frbr/officielepublicaties/gmb/2018/gmb-2018-87384/1/xml/gmb-2018-87384.xml","type":"Overige overheidsinformatie","title":"Milieuinformatie","description":"Milieuinformatie","location":[]},
{"date":"2021-05-09T17:48:35.242Z","urlDoc":"https://zoek.officielebekendmakingen.nl/gmb-2018-87452.html","urlApi":"https://repository.overheid.nl/frbr/officielepublicaties/gmb/2018/gmb-2018-87452/1/xml/gmb-2018-87452.xml","type":"Verordeningen","title":"De Verordening voor het periodiek onderzoek door het college naar de doelmatigheid en doeltreffendheid van het door het college gevoerde bestuur.","description":"De Verordening voor het periodiek onderzoek door het college naar de doelmatigheid en doeltreffendheid van het door het college gevoerde bestuur.","location":[]},
{"date":"2021-10-11T09:42:28.525Z","urlDoc":"https://zoek.officielebekendmakingen.nl/stcrt-2018-22990.html","urlApi":"https://repository.overheid.nl/frbr/officielepublicaties/stcrt/2018/stcrt-2018-22990/1/xml/stcrt-2018-22990.xml","type":"Ruimtelijke plannen","title":"Ontwerp bestemmingsplan ‘Meppel –Haveltermade 2017’","description":"Ontwerp bestemmingsplan ‘Meppel –Haveltermade 2017’","location":["52.7045185666882 6.19534060342163"]}
]}